aps_hmac/__init__.py
aps_hmac/hmac_api_helper.py
aps_hmac-1.0.0.dist-info/LICENSE
aps_hmac-1.0.0.dist-info/METADATA
aps_hmac-1.0.0.dist-info/WHEEL
aps_hmac-1.0.0.dist-info/top_level.txt
aps_hmac-1.0.0.dist-info/RECORD
